README.rst
setup.cfg
setup.py
rind/__init__.py
rind/__version__.py
rind/cli.py
rind/exceptions.py
rind/main.py
rind/service.py
rind.egg-info/PKG-INFO
rind.egg-info/SOURCES.txt
rind.egg-info/dependency_links.txt
rind.egg-info/entry_points.txt
rind.egg-info/requires.txt
rind.egg-info/top_level.txt