Metadata-Version: 1.1
Name: rind
Version: 0.1.0
Summary: Run in Docker
Home-page: https://github.com/a-musing-moose/rind
Author: Jonathan Moss
Author-email: jmoss@commoncode.io
License: MIT
Platform: UNKNOWN
Classifier: Intended Audience :: Developers
Classifier: Topic :: Utilities
Classifier: Programming Language :: Python :: 3.6
